flet_map/__init__.py
flet_map/circle_layer.py
flet_map/map.py
flet_map/map_layer.py
flet_map/marker_layer.py
flet_map/polygon_layer.py
flet_map/polyline_layer.py
flet_map/rich_attribution.py
flet_map/simple_attribution.py
flet_map/source_attribution.py
flet_map/tile_layer.py
flet_map/types.py
flet_map-0.80.5.dist-info/licenses/LICENSE
flutter/flet_map/analysis_options.yaml
flutter/flet_map/pubspec.lock
flutter/flet_map/pubspec.yaml
flutter/flet_map/lib/flet_map.dart
flutter/flet_map/lib/src/circle_layer.dart
flutter/flet_map/lib/src/extension.dart
flutter/flet_map/lib/src/map.dart
flutter/flet_map/lib/src/marker_layer.dart
flutter/flet_map/lib/src/polygon_layer.dart
flutter/flet_map/lib/src/polyline_layer.dart
flutter/flet_map/lib/src/rich_attribution.dart
flutter/flet_map/lib/src/simple_attribution.dart
flutter/flet_map/lib/src/tile_layer.dart
flutter/flet_map/lib/src/utils/attribution_alignment.dart
flutter/flet_map/lib/src/utils/map.dart
flet_map-0.80.5.dist-info/METADATA
flet_map-0.80.5.dist-info/WHEEL
flet_map-0.80.5.dist-info/top_level.txt
flet_map-0.80.5.dist-info/RECORD
